variable_base_factoradic/__init__.py
variable_base_factoradic/variable_base_factoradic.py
variable_base_factoradic-1.2.dist-info/LICENSE.txt
variable_base_factoradic-1.2.dist-info/METADATA
variable_base_factoradic-1.2.dist-info/WHEEL
variable_base_factoradic-1.2.dist-info/RECORD
